{
  "_class": "shapePath",
  "booleanOperation": -1,
  "do_objectID": "31E14606-25E7-40CA-8DC3-6D3D728E3FCE",
  "edited": true,
  "exportOptions": {
    "_class": "exportOptions",
    "do_objectID": "3787D6C2-B247-4CFA-8073-B35165AC1621",
    "exportFormats": [
    ],
    "includedLayerIds": [
    ],
    "layerOptions": 0,
    "shouldTrim": false
  },
  "frame": {
    "_class": "rect",
    "constrainProportions": false,
    "do_objectID": "5BECBA7D-96EE-486D-88BD-B7329A016C85",
    "height": 116.3039014373718,
    "width": 82.79260780287474,
    "x": 0,
    "y": 0
  },
  "isClosed": false,
  "isFixedToViewport": false,
  "isFlippedHorizontal": false,
  "isFlippedVertical": false,
  "isLocked": false,
  "isVisible": true,
  "layerListExpandedType": 0,
  "name": "Path",
  "nameIsFixed": false,
  "pointRadiusBehaviour": 0,
  "points": [
    {
      "_class": "curvePoint",
      "cornerRadius": 0,
      "curveFrom": "{0, 0}",
      "curveMode": 1,
      "curveTo": "{0, 0}",
      "hasCurveFrom": false,
      "hasCurveTo": false,
      "point": "{0, 0}"
    },
    {
      "_class": "curvePoint",
      "cornerRadius": 0,
      "curveFrom": "{1, 0.10428350318599358}",
      "curveMode": 1,
      "curveTo": "{1, 0.10428350318599358}",
      "hasCurveFrom": false,
      "hasCurveTo": false,
      "point": "{1, 0.10428350318599358}"
    },
    {
      "_class": "curvePoint",
      "cornerRadius": 0,
      "curveFrom": "{0.91363521091042454, 1}",
      "curveMode": 1,
      "curveTo": "{0.91363521091042454, 1}",
      "hasCurveFrom": false,
      "hasCurveTo": false,
      "point": "{0.91363521091042454, 1}"
    }
  ],
  "resizingConstraint": 63,
  "resizingType": 0,
  "rotation": 0,
  "shouldBreakMaskChain": false,
  "userInfo": {
    "com.animaapp.stc-sketch-plugin": {
      "kModelPropertiesKey": {
      }
    }
  }
}