{
  "_class": "shapeGroup",
  "booleanOperation": 0,
  "clippingMaskMode": 0,
  "do_objectID": "99E2648C-C599-4CCA-865B-FDDA29A5E8F6",
  "exportOptions": {
    "_class": "exportOptions",
    "do_objectID": "917CD6F7-47F2-4228-B84D-8EC6EF8FE2B2",
    "exportFormats": [
    ],
    "includedLayerIds": [
    ],
    "layerOptions": 0,
    "shouldTrim": false
  },
  "frame": {
    "_class": "rect",
    "constrainProportions": false,
    "do_objectID": "BE0DE872-BB2F-4E20-932A-2A4343CBD0B7",
    "height": 13.70722298287195,
    "width": 12.47980538997763,
    "x": 94.3776804856985,
    "y": 126.0687541476492
  },
  "hasClickThrough": false,
  "hasClippingMask": false,
  "isFixedToViewport": false,
  "isFlippedHorizontal": false,
  "isFlippedVertical": false,
  "isLocked": false,
  "isVisible": true,
  "layerListExpandedType": 0,
  "layers": [
    {
      "class": "shapePath",
      "id": "085989AF-217A-411A-9F43-7D483973E00C"
    }
  ],
  "name": "Path 49",
  "nameIsFixed": false,
  "resizingConstraint": 63,
  "resizingType": 0,
  "rotation": 0,
  "shouldBreakMaskChain": false,
  "style": {
    "_class": "style",
    "borderOptions": {
      "_class": "borderOptions",
      "dashPattern": [
      ],
      "isEnabled": false,
      "lineCapStyle": 1,
      "lineJoinStyle": 1
    },
    "borders": [
      {
        "_class": "border",
        "color": {
          "_class": "color",
          "alpha": 0.12,
          "blue": 0.6588235294117647,
          "green": 0.1764705882352941,
          "red": 0.3176470588235295
        },
        "fillType": 0,
        "isEnabled": true,
        "position": 0,
        "thickness": 3
      }
    ],
    "do_objectID": "C59B47DD-CB7B-4A42-8484-79C87EFFF78C",
    "endMarkerType": 0,
    "fills": [
      {
        "_class": "fill",
        "color": {
          "_class": "color",
          "alpha": 1,
          "blue": 0.847,
          "green": 0.847,
          "red": 0.847
        },
        "fillType": 0,
        "isEnabled": false,
        "noiseIndex": 0,
        "noiseIntensity": 0,
        "patternFillType": 0,
        "patternTileScale": 1
      }
    ],
    "miterLimit": 10,
    "startMarkerType": 0,
    "windingRule": 1
  },
  "userInfo": {
    "com.animaapp.stc-sketch-plugin": {
      "kModelPropertiesKey": {
      }
    }
  },
  "windingRule": 1
}