{
  "_class": "shapePath",
  "booleanOperation": -1,
  "do_objectID": "135AA9BD-DDB8-4294-A88E-A12A9EDEBE58",
  "edited": true,
  "exportOptions": {
    "_class": "exportOptions",
    "do_objectID": "4DB96ED7-E519-4A15-A078-01E36498799C",
    "exportFormats": [
    ],
    "includedLayerIds": [
    ],
    "layerOptions": 0,
    "shouldTrim": false
  },
  "frame": {
    "_class": "rect",
    "constrainProportions": false,
    "do_objectID": "7F00EF7C-1AAA-477D-B3E6-B26CD9C5DA84",
    "height": 18.3717178020732,
    "width": 33.64193629929292,
    "x": 0,
    "y": 0
  },
  "isClosed": false,
  "isFixedToViewport": false,
  "isFlippedHorizontal": false,
  "isFlippedVertical": false,
  "isLocked": false,
  "isVisible": true,
  "layerListExpandedType": 0,
  "name": "Path",
  "nameIsFixed": false,
  "pointRadiusBehaviour": 0,
  "points": [
    {
      "_class": "curvePoint",
      "cornerRadius": 0,
      "curveFrom": "{0, 0}",
      "curveMode": 1,
      "curveTo": "{0, 0}",
      "hasCurveFrom": false,
      "hasCurveTo": false,
      "point": "{0, 0}"
    },
    {
      "_class": "curvePoint",
      "cornerRadius": 0,
      "curveFrom": "{0.32203613693998312, 0.98195714216611052}",
      "curveMode": 1,
      "curveTo": "{0.32203613693998312, 0.98195714216611052}",
      "hasCurveFrom": false,
      "hasCurveTo": false,
      "point": "{0.32203613693998312, 0.98195714216611052}"
    },
    {
      "_class": "curvePoint",
      "cornerRadius": 0,
      "curveFrom": "{0.72722950126796282, 0.27393218207323561}",
      "curveMode": 1,
      "curveTo": "{0.72722950126796282, 0.27393218207323561}",
      "hasCurveFrom": false,
      "hasCurveTo": false,
      "point": "{0.72722950126796282, 0.27393218207323561}"
    },
    {
      "_class": "curvePoint",
      "cornerRadius": 0,
      "curveFrom": "{1, 0.99999999999999989}",
      "curveMode": 1,
      "curveTo": "{1, 0.99999999999999989}",
      "hasCurveFrom": false,
      "hasCurveTo": false,
      "point": "{1, 0.99999999999999989}"
    }
  ],
  "resizingConstraint": 63,
  "resizingType": 0,
  "rotation": 0,
  "shouldBreakMaskChain": false,
  "userInfo": {
    "com.animaapp.stc-sketch-plugin": {
      "kModelPropertiesKey": {
      }
    }
  }
}