{
  "_class": "shapePath",
  "booleanOperation": -1,
  "do_objectID": "EA783F97-18E2-4A1A-82F6-46429B517BB6",
  "edited": true,
  "exportOptions": {
    "_class": "exportOptions",
    "do_objectID": "D09A3E50-0364-4D53-A950-E95F31A5B85F",
    "exportFormats": [
    ],
    "includedLayerIds": [
    ],
    "layerOptions": 0,
    "shouldTrim": false
  },
  "frame": {
    "_class": "rect",
    "constrainProportions": false,
    "do_objectID": "F1C7FE30-9D05-4D2D-A499-371AFA462C4F",
    "height": 11.89855994059658,
    "width": 14.12980473104703,
    "x": -1.77635683940025e-15,
    "y": 0
  },
  "isClosed": false,
  "isFixedToViewport": false,
  "isFlippedHorizontal": false,
  "isFlippedVertical": false,
  "isLocked": false,
  "isVisible": true,
  "layerListExpandedType": 0,
  "name": "Path",
  "nameIsFixed": false,
  "pointRadiusBehaviour": 0,
  "points": [
    {
      "_class": "curvePoint",
      "cornerRadius": 0,
      "curveFrom": "{0.010046423194469549, 1}",
      "curveMode": 1,
      "curveTo": "{0.010046423194469549, 1}",
      "hasCurveFrom": false,
      "hasCurveTo": false,
      "point": "{0.010046423194469549, 1}"
    },
    {
      "_class": "curvePoint",
      "cornerRadius": 0,
      "curveFrom": "{2.1705855128020684, -0.084322951676749566}",
      "curveMode": 2,
      "curveTo": "{-0.17058551280206835, 0.084322951676749539}",
      "hasCurveFrom": true,
      "hasCurveTo": true,
      "point": "{1, 0}"
    }
  ],
  "resizingConstraint": 63,
  "resizingType": 0,
  "rotation": 0,
  "shouldBreakMaskChain": false,
  "userInfo": {
    "com.animaapp.stc-sketch-plugin": {
      "kModelPropertiesKey": {
      }
    }
  }
}