{
  "_class": "group",
  "booleanOperation": -1,
  "do_objectID": "4D3A669E-F18A-49E2-ABE2-F22824350EEB",
  "exportOptions": {
    "_class": "exportOptions",
    "exportFormats": [
    ],
    "includedLayerIds": [
    ],
    "layerOptions": 0,
    "shouldTrim": false
  },
  "frame": {
    "_class": "rect",
    "constrainProportions": false,
    "height": 120,
    "width": 376,
    "x": 0,
    "y": 64
  },
  "hasClickThrough": false,
  "isFixedToViewport": false,
  "isFlippedHorizontal": false,
  "isFlippedVertical": false,
  "isLocked": false,
  "isVisible": false,
  "layerListExpandedType": 2,
  "layers": [
    {
      "class": "shapeGroup",
      "id": "187F2FEC-170D-4993-BB7E-A0B7C66A2A4D"
    },
    {
      "class": "group",
      "id": "F2DB5959-728D-4B36-AA73-ED7C43663E61"
    },
    {
      "class": "text",
      "id": "9E8FE577-F5B1-4D4F-A5B9-6E9423946BA7"
    },
    {
      "class": "text",
      "id": "35E34F72-58F9-4FB7-A2E7-C3823979C108"
    }
  ],
  "name": "Group 6",
  "nameIsFixed": false,
  "resizingConstraint": 63,
  "resizingType": 0,
  "rotation": 0,
  "shouldBreakMaskChain": false,
  "style": {
    "_class": "style",
    "endMarkerType": 0,
    "miterLimit": 10,
    "startMarkerType": 0,
    "windingRule": 1
  }
}