{
  "_class": "shapeGroup",
  "booleanOperation": 0,
  "clippingMaskMode": 0,
  "do_objectID": "62EDA03E-0EE6-4E20-AA4D-CE8A2D1E571C",
  "exportOptions": {
    "_class": "exportOptions",
    "do_objectID": "03609B8C-77B3-4890-BD37-8631AA6C17B5",
    "exportFormats": [
    ],
    "includedLayerIds": [
    ],
    "layerOptions": 0,
    "shouldTrim": false
  },
  "frame": {
    "_class": "rect",
    "constrainProportions": false,
    "do_objectID": "B52A68C0-F0CB-4166-92D9-38DA649E1EB7",
    "height": 94.62012320328546,
    "width": 45.33880903490763,
    "x": 583.4907597535934,
    "y": 480.9856262833676
  },
  "hasClickThrough": false,
  "hasClippingMask": false,
  "isFixedToViewport": false,
  "isFlippedHorizontal": false,
  "isFlippedVertical": false,
  "isLocked": false,
  "isVisible": true,
  "layerListExpandedType": 0,
  "layers": [
    {
      "class": "shapePath",
      "id": "78B4DD9F-B599-48E2-AF2A-15987B765CCE"
    }
  ],
  "name": "Path 202",
  "nameIsFixed": false,
  "resizingConstraint": 63,
  "resizingType": 0,
  "rotation": 0,
  "shouldBreakMaskChain": false,
  "style": {
    "_class": "style",
    "borderOptions": {
      "_class": "borderOptions",
      "dashPattern": [
      ],
      "do_objectID": "1596D198-3736-418D-BF8C-F8B06D2D5E7E",
      "isEnabled": false,
      "lineCapStyle": 1,
      "lineJoinStyle": 1
    },
    "borders": [
      {
        "_class": "border",
        "color": {
          "_class": "color",
          "alpha": 0.12,
          "blue": 0.6588235294117647,
          "green": 0.1764705882352941,
          "red": 0.3176470588235295
        },
        "fillType": 0,
        "isEnabled": true,
        "position": 0,
        "thickness": 3
      }
    ],
    "do_objectID": "47BA461C-ACD7-4978-A116-56962FC160F5",
    "endMarkerType": 0,
    "fills": [
      {
        "_class": "fill",
        "color": {
          "_class": "color",
          "alpha": 1,
          "blue": 0.847,
          "green": 0.847,
          "red": 0.847
        },
        "fillType": 0,
        "isEnabled": false,
        "noiseIndex": 0,
        "noiseIntensity": 0,
        "patternFillType": 0,
        "patternTileScale": 1
      }
    ],
    "miterLimit": 10,
    "startMarkerType": 0,
    "windingRule": 1
  },
  "userInfo": {
    "com.animaapp.stc-sketch-plugin": {
      "kModelPropertiesKey": {
      }
    }
  },
  "windingRule": 1
}