{
  "_class": "shapeGroup",
  "booleanOperation": 0,
  "clippingMaskMode": 0,
  "do_objectID": "704FFFBC-5606-493C-BA4D-DBEE46693A21",
  "exportOptions": {
    "_class": "exportOptions",
    "do_objectID": "BCED04C2-6688-4997-B446-66447AABB56F",
    "exportFormats": [
    ],
    "includedLayerIds": [
    ],
    "layerOptions": 0,
    "shouldTrim": false
  },
  "frame": {
    "_class": "rect",
    "constrainProportions": false,
    "do_objectID": "9A07B99D-DEBB-4FB4-B61A-79C7C3FF433B",
    "height": 39.42505133470218,
    "width": 35.48254620123203,
    "x": 433.6755646817248,
    "y": 802.2997946611911
  },
  "hasClickThrough": false,
  "hasClippingMask": false,
  "isFixedToViewport": false,
  "isFlippedHorizontal": false,
  "isFlippedVertical": false,
  "isLocked": false,
  "isVisible": true,
  "layerListExpandedType": 0,
  "layers": [
    {
      "class": "shapePath",
      "id": "8A8A9324-6CEC-48B7-927A-F7B88EEF15B0"
    }
  ],
  "name": "Path 101",
  "nameIsFixed": false,
  "resizingConstraint": 63,
  "resizingType": 0,
  "rotation": 0,
  "shouldBreakMaskChain": false,
  "style": {
    "_class": "style",
    "borderOptions": {
      "_class": "borderOptions",
      "dashPattern": [
      ],
      "do_objectID": "0076BA9A-48D4-4025-AD1B-D79E34EC5EE9",
      "isEnabled": false,
      "lineCapStyle": 1,
      "lineJoinStyle": 1
    },
    "borders": [
      {
        "_class": "border",
        "color": {
          "_class": "color",
          "alpha": 0.12,
          "blue": 0.6588235294117647,
          "green": 0.1764705882352941,
          "red": 0.3176470588235295
        },
        "fillType": 0,
        "isEnabled": true,
        "position": 0,
        "thickness": 3
      }
    ],
    "do_objectID": "94FC5DC2-AC5A-404B-BF27-40F503A86984",
    "endMarkerType": 0,
    "fills": [
      {
        "_class": "fill",
        "color": {
          "_class": "color",
          "alpha": 1,
          "blue": 0.847,
          "green": 0.847,
          "red": 0.847
        },
        "fillType": 0,
        "isEnabled": false,
        "noiseIndex": 0,
        "noiseIntensity": 0,
        "patternFillType": 0,
        "patternTileScale": 1
      }
    ],
    "miterLimit": 10,
    "startMarkerType": 0,
    "windingRule": 1
  },
  "userInfo": {
    "com.animaapp.stc-sketch-plugin": {
      "kModelPropertiesKey": {
      }
    }
  },
  "windingRule": 1
}